CHANGES.txt
LICENSE.txt
README.txt
bootstrap.py
setup.py
src/p01/__init__.py
src/p01.widget.password.egg-info/PKG-INFO
src/p01.widget.password.egg-info/SOURCES.txt
src/p01.widget.password.egg-info/dependency_links.txt
src/p01.widget.password.egg-info/namespace_packages.txt
src/p01.widget.password.egg-info/not-zip-safe
src/p01.widget.password.egg-info/requires.txt
src/p01.widget.password.egg-info/top_level.txt
src/p01/widget/__init__.py
src/p01/widget/password/README.txt
src/p01/widget/password/__init__.py
src/p01/widget/password/configure.zcml
src/p01/widget/password/input.pt
src/p01/widget/password/interfaces.py
src/p01/widget/password/tests.py
src/p01/widget/password/widget.py