Metadata-Version: 1.0
Name: p01.widget.password
Version: 0.5.0
Summary: Password widget incl. confirmation field based on z3c.form for Zope3
Home-page: http://cheeseshop.python.org/pypi/p01.widget.password
Author: Roger Ineichen, Projekt01 GmbH
Author-email: dev@projekt01.ch
License: ZPL 2.1
Keywords: zope3 z3c form password confirmation widget p01
Platform: UNKNOWN
Classifier: Development Status :: 4 - Beta
Classifier: Environment :: Web Environment
Classifier: Intended Audience :: Developers
Classifier: License :: OSI Approved :: Zope Public License
Classifier: Programming Language :: Python
Classifier: Natural Language :: English
Classifier: Operating System :: OS Independent
Classifier: Topic :: Internet :: WWW/HTTP
Classifier: Framework :: Zope3
